qptifffile/__init__.py
qptifffile/qptifffile.py
qptifffile-0.0.2.dist-info/licenses/LICENSE
qptifffile-0.0.2.dist-info/METADATA
qptifffile-0.0.2.dist-info/WHEEL
qptifffile-0.0.2.dist-info/top_level.txt
qptifffile-0.0.2.dist-info/RECORD
