Metadata-Version: 2.4
Name: qptifffile
Version: 0.0.2
Summary: A package for working with Perkin Elmer/Akoya Biosciences QPTIFF files
Home-page: https://github.com/grenkoca/qptifffile
Author: Caleb Grenko
Author-email: grenkoca@gmail.com
Project-URL: Bug Tracker, https://github.com/grenkoca/qptifffile/issues
Classifier: Programming Language :: Python :: 3
Classifier: License :: OSI Approved :: MIT License
Classifier: Operating System :: OS Independent
Requires-Python: >=3.6
License-File: LICENSE
Requires-Dist: tifffile
Requires-Dist: numpy
Requires-Dist: imagecodecs
Dynamic: license-file
